[
  {
    "nome": "Bola de Fogo",
    "nivel": 3,
    "escola": "Evocação",
    "descricao": "Uma explosão flamejante atinge uma área causando 8d6 de dano de fogo."
  },
  {
    "nome": "Mísseis Mágicos",
    "nivel": 1,
    "escola": "Evocação",
    "descricao": "Projéteis mágicos que acertam automaticamente, causando 1d4+1 de dano cada."
  },
  {
    "nome": "Toque Arrepiante",
    "nivel": 0,
    "escola": "Necromancia",
    "descricao": "Um toque espectral causa dano necrótico e impede a cura do alvo por 1 turno."
  },
  {
    "nome": "Imobilizar Pessoa",
    "nivel": 2,
    "escola": "Encantamento",
    "descricao": "Paralisa um humanoide se ele falhar num teste de resistência de Sabedoria."
  }
]
